MANIFEST.in
README.txt
setup.py
docs/HISTORY.txt
docs/INSTALL.txt
docs/LICENSE.txt
pas/__init__.py
pas.plugins.external_auth.egg-info/PKG-INFO
pas.plugins.external_auth.egg-info/SOURCES.txt
pas.plugins.external_auth.egg-info/dependency_links.txt
pas.plugins.external_auth.egg-info/entry_points.txt
pas.plugins.external_auth.egg-info/namespace_packages.txt
pas.plugins.external_auth.egg-info/not-zip-safe
pas.plugins.external_auth.egg-info/requires.txt
pas.plugins.external_auth.egg-info/top_level.txt
pas/plugins/__init__.py
pas/plugins/external_auth/__init__.py
pas/plugins/external_auth/configure.zcml
pas/plugins/external_auth/manage_configure.pt
pas/plugins/external_auth/plugin.py
pas/plugins/external_auth/locales/pas.plugins.external_auth-manual.pot
pas/plugins/external_auth/locales/pas.plugins.external_auth.pot
pas/plugins/external_auth/locales/update.sh
pas/plugins/external_auth/locales/fr/LC_MESSAGES/pas.plugins.external_auth.mo
pas/plugins/external_auth/locales/fr/LC_MESSAGES/pas.plugins.external_auth.po
pas/plugins/external_auth/profiles/default/pas_plugins.xml
pas/plugins/external_auth/profiles/default-plone/pas_plugins.xml
pas/plugins/external_auth/profiles/default-plone/skins.xml
pas/plugins/external_auth/profiles/default-plone/acl_users/.objects
pas/plugins/external_auth/profiles/default-plone/acl_users/.preserve
pas/plugins/external_auth/profiles/default-plone/acl_users/dyn_groups.xml
pas/plugins/external_auth/profiles/default-plone/acl_users/dyn_users.xml
pas/plugins/external_auth/profiles/default-plone/acl_users/external_auth/.objects
pas/plugins/external_auth/profiles/default-plone/acl_users/external_auth/.properties
pas/plugins/external_auth/profiles/default-plone3/pas_plugins.xml
pas/plugins/external_auth/profiles/default-plone3/skins.xml
pas/plugins/external_auth/profiles/default-plone3/acl_users/.objects
pas/plugins/external_auth/profiles/default-plone3/acl_users/.preserve
pas/plugins/external_auth/profiles/default-plone3/acl_users/dyn_groups.xml
pas/plugins/external_auth/profiles/default-plone3/acl_users/dyn_users.xml
pas/plugins/external_auth/profiles/default-plone3/acl_users/external_auth/.objects
pas/plugins/external_auth/profiles/default-plone3/acl_users/external_auth/.properties
pas/plugins/external_auth/profiles/default-plone3_uninstall/pas_plugins.xml
pas/plugins/external_auth/profiles/default-plone3_uninstall/skins.xml
