Metadata-Version: 1.0
Name: pas.plugins.external-auth
Version: 0.1rc2
Summary: A plugin to allow external authentication informations (commonly headers from apache to work with most SSO) to create users and groups.
Home-page: http://www.smile-suisse.com/
Author: Maric Michaud
Author-email: maric.michaud@smile-suisse.com
License: GPL
Keywords: Zope Authentication SSO Shibboleth PluggableAuthService
Platform: UNKNOWN
Classifier: Development Status :: 4 - Beta
Classifier: Framework :: Zope2
Classifier: Programming Language :: Python
Classifier: License :: OSI Approved :: GNU General Public License v3 or later (GPLv3+)
Classifier: Operating System :: OS Independent
